[
  {
    "year": 2024,
    "achievements": [
      {
        "title": "Master Software Engineer - University of Amsterdam",
        "description": "Education"
      }
    ]
  },
  {
    "year": 2024,
    "achievements": [
      {
        "title": "Rabobank Utrecht, Current Account & Routing",
        "description": "Internship"
      }
    ]
  },
  {
    "year": 2024,
    "achievements": [
      {
        "title": "CERN Alice, Software Engineer Placement",
        "description": "Internship"
      }
    ]
  },
  {
    "year": 2023,
    "achievements": [
      {
        "title": "Pre-master Software Engineer - University of Amsterdam",
        "description": "Education"
      }
    ]
  },
  {
    "year": 2023,
    "achievements": [
      {
        "title": "Amsterdam Internet Exchange, Software Engineer Placement",
        "description": "Internship"
      }
    ]
  },
  {
    "year": 2022,
    "achievements": [
      {
        "title": "University of Applied Sciences Amsterdam · Student Assistent",
        "description": "Parttime"
      }
    ]
  },
  {
    "year": 2021,
    "achievements": [
      {
        "title": "Rabobank Utrecht, FLR Channel Management",
        "description": "Internship"
      }
    ]
  },
  {
    "year": 2020,
    "achievements": [
      {
        "title": "HBO ICT Software Engineer - University of Applied Sciences Amsterdam",
        "description": "Education"
      }
    ]
  },
  {
    "year": 2019,
    "achievements": [
      {
        "title": "BlueBloq - SEO & Online marketing",
        "description": "Internship, Parttime"
      }
    ]
  },
  {
    "year": 2018,
    "achievements": [
      {
        "title": "Blue Mammoth - WordPress specialist",
        "description": "Internship, Parttime"
      }
    ]
  }
]